<?xml version="1.0" encoding="utf-8"?>
<updates>
    <update>
        <name>Health Checker - Akeeba Admin Tools Integration</name>
        <description>Optional Akeeba Admin Tools integration plugin</description>
        <element>akeebaadmintools</element>
        <type>plugin</type>
        <client>site</client>
        <folder>healthchecker</folder>
        <version>3.2.3</version>
        <infourl title="Health Checker">https://github.com/mySites-guru/HealthCheckerForJoomla</infourl>
        <downloads>
            <downloadurl type="full" format="zip">https://www.joomlahealthchecker.com/downloads/plg_healthchecker_akeebaadmintools-3.2.3.zip</downloadurl>
        </downloads>
        <sha512>24f99bde57913b80e30ea89c91b6b0f6d484a5542033aa0b30445b691f0592987b554577013cdb39e9d85ea60fa5a28ee7f7056be1d1fbdbdac14335bfd440e7</sha512>
        <tags>
            <tag>stable</tag>
        </tags>
        <maintainer>mySites.guru / Phil E. Taylor</maintainer>
        <maintainerurl>https://www.phil-taylor.com</maintainerurl>
        <targetplatform name="joomla" version="(5|6)\.[0-9]+" />
        <php_minimum>8.1.0</php_minimum>
    </update>
</updates>
